{"__cls__": "SaveBundle", "transfer_mx": "{\"res_0_node_5\": {\"res_0_node_5\": 0, \"res_0_node_4\": 402933007, \"res_0_node_7\": 421586858, \"res_0_node_6\": 772957322, \"res_0_node_1\": 113192167, \"res_0_node_0\": 763356781, \"res_0_node_3\": 841347414, \"res_0_node_2\": 732294063, \"res_0_node_9\": 874058811, \"res_0_node_8\": 588049483}, \"res_0_node_4\": {\"res_0_node_5\": 434436028, \"res_0_node_4\": 0, \"res_0_node_7\": 716617792, \"res_0_node_6\": 378519704, \"res_0_node_1\": 978946407, \"res_0_node_0\": 144687089, \"res_0_node_3\": 721296364, \"res_0_node_2\": 444754115, \"res_0_node_9\": 1007119052, \"res_0_node_8\": 827039544}, \"res_0_node_7\": {\"res_0_node_5\": 141114712, \"res_0_node_4\": 158276181, \"res_0_node_7\": 0, \"res_0_node_6\": 356840006, \"res_0_node_1\": 829372280, \"res_0_node_0\": 808666495, \"res_0_node_3\": 584343915, \"res_0_node_2\": 498489504, \"res_0_node_9\": 29414364, \"res_0_node_8\": 182416298}, \"res_0_node_6\": {\"res_0_node_5\": 305533265, \"res_0_node_4\": 26423920, \"res_0_node_7\": 7727186, \"res_0_node_6\": 0, \"res_0_node_1\": 966686603, \"res_0_node_0\": 270064683, \"res_0_node_3\": 516250154, \"res_0_node_2\": 221323431, \"res_0_node_9\": 80834552, \"res_0_node_8\": 550370720}, \"res_0_node_1\": {\"res_0_node_5\": 77014630, \"res_0_node_4\": 290903954, \"res_0_node_7\": 500033335, \"res_0_node_6\": 210556033, \"res_0_node_1\": 0, \"res_0_node_0\": 323560556, \"res_0_node_3\": 510843385, \"res_0_node_2\": 827843872, \"res_0_node_9\": 799685641, \"res_0_node_8\": 443528629}, \"res_0_node_0\": {\"res_0_node_5\": 1012597503, \"res_0_node_4\": 470851853, \"res_0_node_7\": 963390165, \"res_0_node_6\": 645176906, \"res_0_node_1\": 1037202826, \"res_0_node_0\": 0, \"res_0_node_3\": 329557983, \"res_0_node_2\": 1009080769, \"res_0_node_9\": 81788953, \"res_0_node_8\": 451411346}, \"res_0_node_3\": {\"res_0_node_5\": 646385871, \"res_0_node_4\": 988574818, \"res_0_node_7\": 325112844, \"res_0_node_6\": 459244900, \"res_0_node_1\": 878134966, \"res_0_node_0\": 246690509, \"res_0_node_3\": 0, \"res_0_node_2\": 982367071, \"res_0_node_9\": 932795611, \"res_0_node_8\": 416739326}, \"res_0_node_2\": {\"res_0_node_5\": 504432743, \"res_0_node_4\": 156906073, \"res_0_node_7\": 855950903, \"res_0_node_6\": 920655863, \"res_0_node_1\": 671679369, \"res_0_node_0\": 965329598, \"res_0_node_3\": 779295938, \"res_0_node_2\": 0, \"res_0_node_9\": 893091709, \"res_0_node_8\": 987512060}, \"res_0_node_9\": {\"res_0_node_5\": 976894095, \"res_0_node_4\": 537110697, \"res_0_node_7\": 361027068, \"res_0_node_6\": 360893838, \"res_0_node_1\": 765744846, \"res_0_node_0\": 776017858, \"res_0_node_3\": 910756773, \"res_0_node_2\": 922987491, \"res_0_node_9\": 0, \"res_0_node_8\": 720929819}, \"res_0_node_8\": {\"res_0_node_5\": 27400236, \"res_0_node_4\": 90804401, \"res_0_node_7\": 149957377, \"res_0_node_6\": 846868291, \"res_0_node_1\": 1056283215, \"res_0_node_0\": 828256309, \"res_0_node_3\": 790645284, \"res_0_node_2\": 889909161, \"res_0_node_9\": 998618957, \"res_0_node_8\": 0}}", "dedicated_resources": [{"__cls__": "Resource", "nodes": [{"resource": "res_0", "__cls__": "Node", "flops": 20, "soft": ["any_soft"], "name": "res_0_node_0"}, {"resource": "res_0", "__cls__": "Node", "flops": 11, "soft": ["any_soft"], "name": "res_0_node_5"}, {"resource": "res_0", "__cls__": "Node", "flops": 11, "soft": ["any_soft"], "name": "res_0_node_1"}, {"resource": "res_0", "__cls__": "Node", "flops": 5, "soft": ["any_soft"], "name": "res_0_node_7"}, {"resource": "res_0", "__cls__": "Node", "flops": 16, "soft": ["any_soft"], "name": "res_0_node_3"}, {"resource": "res_0", "__cls__": "Node", "flops": 5, "soft": ["any_soft"], "name": "res_0_node_2"}, {"resource": "res_0", "__cls__": "Node", "flops": 20, "soft": ["any_soft"], "name": "res_0_node_4"}, {"resource": "res_0", "__cls__": "Node", "flops": 11, "soft": ["any_soft"], "name": "res_0_node_6"}, {"resource": "res_0", "__cls__": "Node", "flops": 18, "soft": ["any_soft"], "name": "res_0_node_8"}, {"resource": "res_0", "__cls__": "Node", "flops": 11, "soft": ["any_soft"], "name": "res_0_node_9"}], "name": "res_0"}], "ga_schedule": {"__cls__": "Schedule", "mapping": [{"value": [{"job": "ID00017_000", "__cls__": "ScheduleItem", "start_time": 223.20999999999998, "state": "finished", "end_time": 225.99181818181816}, {"job": "ID00027_000", "__cls__": "ScheduleItem", "start_time": 225.99181818181816, "state": "finished", "end_time": 227.99181818181816}], "node": "res_0_node_9"}, {"value": [{"job": "ID00022_000", "__cls__": "ScheduleItem", "start_time": 101.91, "state": "finished", "end_time": 226.11}], "node": "res_0_node_2"}, {"value": [{"job": "ID00013_000", "__cls__": "ScheduleItem", "start_time": 0, "state": "finished", "end_time": 96.91}, {"job": "ID00024_000", "__cls__": "ScheduleItem", "start_time": 96.91, "state": "finished", "end_time": 151.77999999999997}, {"job": "ID00018_000", "__cls__": "ScheduleItem", "start_time": 151.77999999999997, "state": "finished", "end_time": 180.45}, {"job": "ID00012_000", "__cls__": "ScheduleItem", "start_time": 281.28181818181815, "state": "finished", "end_time": 282.70181818181817}, {"job": "ID00000_000", "__cls__": "ScheduleItem", "start_time": 282.70181818181817, "state": "finished", "end_time": 282.77181818181816}], "node": "res_0_node_4"}, {"value": [{"job": "ID00003_000", "__cls__": "ScheduleItem", "start_time": 163.1, "state": "finished", "end_time": 234.11818181818182}, {"job": "ID00006_000", "__cls__": "ScheduleItem", "start_time": 234.11818181818182, "state": "finished", "end_time": 235.5727272727273}], "node": "res_0_node_6"}, {"value": [{"job": "ID00002_000", "__cls__": "ScheduleItem", "start_time": 0, "state": "finished", "end_time": 158.1}, {"job": "ID00005_000", "__cls__": "ScheduleItem", "start_time": 158.1, "state": "finished", "end_time": 196.59}, {"job": "ID00009_000", "__cls__": "ScheduleItem", "start_time": 196.59, "state": "finished", "end_time": 228.88}, {"job": "ID00025_000", "__cls__": "ScheduleItem", "start_time": 228.88, "state": "finished", "end_time": 229.66}], "node": "res_0_node_0"}, {"value": [{"job": "ID00011_000", "__cls__": "ScheduleItem", "start_time": 163.1, "state": "finished", "end_time": 276.28181818181815}], "node": "res_0_node_5"}, {"value": [{"job": "ID00020_000", "__cls__": "ScheduleItem", "start_time": 101.91, "state": "finished", "end_time": 146.56454545454545}, {"job": "ID00026_000", "__cls__": "ScheduleItem", "start_time": 146.56454545454545, "state": "finished", "end_time": 190.18272727272728}, {"job": "ID00021_000", "__cls__": "ScheduleItem", "start_time": 190.18272727272728, "state": "finished", "end_time": 192.65545454545455}], "node": "res_0_node_1"}, {"value": [{"job": "ID00015_000", "__cls__": "ScheduleItem", "start_time": 166.20999999999998, "state": "finished", "end_time": 167.90999999999997}, {"job": "ID00019_000", "__cls__": "ScheduleItem", "start_time": 185.45, "state": "finished", "end_time": 186.9611111111111}, {"job": "ID00029_000", "__cls__": "ScheduleItem", "start_time": 212.75, "state": "finished", "end_time": 213.69444444444446}, {"job": "ID00001_000", "__cls__": "ScheduleItem", "start_time": 281.28181818181815, "state": "finished", "end_time": 281.49292929292926}], "node": "res_0_node_8"}, {"value": [{"job": "ID00028_000", "__cls__": "ScheduleItem", "start_time": 101.91, "state": "finished", "end_time": 207.75}, {"job": "ID00010_000", "__cls__": "ScheduleItem", "start_time": 233.88, "state": "finished", "end_time": 236.84}, {"job": "ID00004_000", "__cls__": "ScheduleItem", "start_time": 239.11818181818182, "state": "finished", "end_time": 241.63818181818183}], "node": "res_0_node_7"}, {"value": [{"job": "ID00014_000", "__cls__": "ScheduleItem", "start_time": 101.91, "state": "finished", "end_time": 161.20999999999998}, {"job": "ID00016_000", "__cls__": "ScheduleItem", "start_time": 161.20999999999998, "state": "finished", "end_time": 218.20999999999998}, {"job": "ID00007_000", "__cls__": "ScheduleItem", "start_time": 218.20999999999998, "state": "finished", "end_time": 263.5475}, {"job": "ID00023_000", "__cls__": "ScheduleItem", "start_time": 263.5475, "state": "finished", "end_time": 265.33500000000004}, {"job": "ID00008_000", "__cls__": "ScheduleItem", "start_time": 265.33500000000004, "state": "finished", "end_time": 266.24750000000006}], "node": "res_0_node_3"}]}, "wf_name": "CyberShake_30", "name": "CyberShake_30_bundle", "ideal_flops": 20}