{"ga_schedule": {"mapping": [{"value": [{"end_time": 18.066666666666666, "state": "finished", "__cls__": "ScheduleItem", "job": "ID00010_000", "start_time": 0}, {"end_time": 35.61333333333333, "state": "finished", "__cls__": "ScheduleItem", "job": "ID00004_000", "start_time": 18.066666666666666}, {"end_time": 53.17333333333333, "state": "finished", "__cls__": "ScheduleItem", "job": "ID00014_000", "start_time": 35.61333333333333}, {"end_time": 67.36, "state": "finished", "__cls__": "ScheduleItem", "job": "ID00061_000", "start_time": 53.17333333333333}, {"end_time": 124.68, "state": "finished", "__cls__": "ScheduleItem", "job": "ID00034_000", "start_time": 110.64}, {"end_time": 138.82666666666668, "state": "finished", "__cls__": "ScheduleItem", "job": "ID00068_000", "start_time": 124.68}, {"end_time": 153.05333333333334, "state": "finished", "__cls__": "ScheduleItem", "job": "ID00027_000", "start_time": 138.82666666666668}, {"end_time": 167.06666666666666, "state": "finished", "__cls__": "ScheduleItem", "job": "ID00040_000", "start_time": 153.05333333333334}, {"end_time": 181.29333333333332, "state": "finished", "__cls__": "ScheduleItem", "job": "ID00036_000", "start_time": 167.06666666666666}, {"end_time": 195.37333333333333, "state": "finished", "__cls__": "ScheduleItem", "job": "ID00045_000", "start_time": 181.29333333333332}, {"end_time": 212.54666666666665, "state": "finished", "__cls__": "ScheduleItem", "job": "ID00046_000", "start_time": 198.38666666666666}], "node": "res_0_node_1"}, {"value": [{"end_time": 27.139999999999997, "state": "finished", "__cls__": "ScheduleItem", "job": "ID00005_000", "start_time": 0}, {"end_time": 142.068, "state": "finished", "__cls__": "ScheduleItem", "job": "ID00055_000", "start_time": 121.128}, {"end_time": 163.388, "state": "finished", "__cls__": "ScheduleItem", "job": "ID00052_000", "start_time": 142.068}, {"end_time": 184.768, "state": "finished", "__cls__": "ScheduleItem", "job": "ID00049_000", "start_time": 163.388}, {"end_time": 205.848, "state": "finished", "__cls__": "ScheduleItem", "job": "ID00044_000", "start_time": 184.768}], "node": "res_0_node_0"}, {"value": [{"end_time": 10.64, "state": "finished", "__cls__": "ScheduleItem", "job": "ID00003_000", "start_time": 0}, {"end_time": 21.128, "state": "finished", "__cls__": "ScheduleItem", "job": "ID00001_000", "start_time": 10.64}, {"end_time": 32.208, "state": "finished", "__cls__": "ScheduleItem", "job": "ID00000_000", "start_time": 21.128}, {"end_time": 40.568, "state": "finished", "__cls__": "ScheduleItem", "job": "ID00020_000", "start_time": 32.208}, {"end_time": 49.024, "state": "finished", "__cls__": "ScheduleItem", "job": "ID00016_000", "start_time": 40.568}, {"end_time": 59.92, "state": "finished", "__cls__": "ScheduleItem", "job": "ID00012_000", "start_time": 49.024}, {"end_time": 68.312, "state": "finished", "__cls__": "ScheduleItem", "job": "ID00032_000", "start_time": 59.92}, {"end_time": 79.232, "state": "finished", "__cls__": "ScheduleItem", "job": "ID00007_000", "start_time": 68.312}, {"end_time": 87.824, "state": "finished", "__cls__": "ScheduleItem", "job": "ID00023_000", "start_time": 79.232}, {"end_time": 96.264, "state": "finished", "__cls__": "ScheduleItem", "job": "ID00031_000", "start_time": 87.824}, {"end_time": 104.8, "state": "finished", "__cls__": "ScheduleItem", "job": "ID00026_000", "start_time": 96.264}, {"end_time": 113.376, "state": "finished", "__cls__": "ScheduleItem", "job": "ID00066_000", "start_time": 104.8}, {"end_time": 126.45066666666666, "state": "finished", "__cls__": "ScheduleItem", "job": "ID00056_000", "start_time": 118.06666666666666}, {"end_time": 134.96266666666668, "state": "finished", "__cls__": "ScheduleItem", "job": "ID00021_000", "start_time": 126.45066666666666}, {"end_time": 143.59466666666668, "state": "finished", "__cls__": "ScheduleItem", "job": "ID00072_000", "start_time": 134.96266666666668}, {"end_time": 152.10666666666668, "state": "finished", "__cls__": "ScheduleItem", "job": "ID00019_000", "start_time": 143.59466666666668}, {"end_time": 160.57066666666668, "state": "finished", "__cls__": "ScheduleItem", "job": "ID00022_000", "start_time": 152.10666666666668}, {"end_time": 169.03466666666668, "state": "finished", "__cls__": "ScheduleItem", "job": "ID00039_000", "start_time": 160.57066666666668}, {"end_time": 177.51466666666667, "state": "finished", "__cls__": "ScheduleItem", "job": "ID00017_000", "start_time": 169.03466666666668}, {"end_time": 185.97866666666667, "state": "finished", "__cls__": "ScheduleItem", "job": "ID00018_000", "start_time": 177.51466666666667}, {"end_time": 194.35466666666667, "state": "finished", "__cls__": "ScheduleItem", "job": "ID00076_000", "start_time": 185.97866666666667}, {"end_time": 202.69866666666667, "state": "finished", "__cls__": "ScheduleItem", "job": "ID00071_000", "start_time": 194.35466666666667}, {"end_time": 211.13066666666666, "state": "finished", "__cls__": "ScheduleItem", "job": "ID00037_000", "start_time": 202.69866666666667}, {"end_time": 219.57866666666666, "state": "finished", "__cls__": "ScheduleItem", "job": "ID00054_000", "start_time": 211.13066666666666}, {"end_time": 228.05066666666667, "state": "finished", "__cls__": "ScheduleItem", "job": "ID00058_000", "start_time": 219.57866666666666}, {"end_time": 236.43466666666666, "state": "finished", "__cls__": "ScheduleItem", "job": "ID00048_000", "start_time": 228.05066666666667}, {"end_time": 244.94666666666666, "state": "finished", "__cls__": "ScheduleItem", "job": "ID00064_000", "start_time": 236.43466666666666}, {"end_time": 253.53866666666667, "state": "finished", "__cls__": "ScheduleItem", "job": "ID00029_000", "start_time": 244.94666666666666}, {"end_time": 261.99466666666666, "state": "finished", "__cls__": "ScheduleItem", "job": "ID00067_000", "start_time": 253.53866666666667}, {"end_time": 270.36266666666666, "state": "finished", "__cls__": "ScheduleItem", "job": "ID00062_000", "start_time": 261.99466666666666}, {"end_time": 278.73066666666665, "state": "finished", "__cls__": "ScheduleItem", "job": "ID00042_000", "start_time": 270.36266666666666}, {"end_time": 287.20266666666663, "state": "finished", "__cls__": "ScheduleItem", "job": "ID00065_000", "start_time": 278.73066666666665}, {"end_time": 295.8186666666666, "state": "finished", "__cls__": "ScheduleItem", "job": "ID00070_000", "start_time": 287.20266666666663}, {"end_time": 304.2106666666666, "state": "finished", "__cls__": "ScheduleItem", "job": "ID00060_000", "start_time": 295.8186666666666}, {"end_time": 312.6026666666666, "state": "finished", "__cls__": "ScheduleItem", "job": "ID00074_000", "start_time": 304.2106666666666}, {"end_time": 316.5706666666666, "state": "finished", "__cls__": "ScheduleItem", "job": "ID00078_000", "start_time": 312.6026666666666}, {"end_time": 320.8426666666666, "state": "finished", "__cls__": "ScheduleItem", "job": "ID00079_000", "start_time": 316.5706666666666}, {"end_time": 329.37066666666664, "state": "finished", "__cls__": "ScheduleItem", "job": "ID00084_000", "start_time": 320.8426666666666}, {"end_time": 338.0586666666666, "state": "finished", "__cls__": "ScheduleItem", "job": "ID00089_000", "start_time": 329.37066666666664}, {"end_time": 346.63466666666665, "state": "finished", "__cls__": "ScheduleItem", "job": "ID00088_000", "start_time": 338.0586666666666}, {"end_time": 355.22666666666663, "state": "finished", "__cls__": "ScheduleItem", "job": "ID00092_000", "start_time": 346.63466666666665}, {"end_time": 363.71466666666663, "state": "finished", "__cls__": "ScheduleItem", "job": "ID00082_000", "start_time": 355.22666666666663}, {"end_time": 372.31466666666665, "state": "finished", "__cls__": "ScheduleItem", "job": "ID00087_000", "start_time": 363.71466666666663}, {"end_time": 380.70666666666665, "state": "finished", "__cls__": "ScheduleItem", "job": "ID00085_000", "start_time": 372.31466666666665}, {"end_time": 389.25866666666667, "state": "finished", "__cls__": "ScheduleItem", "job": "ID00091_000", "start_time": 380.70666666666665}, {"end_time": 397.8826666666667, "state": "finished", "__cls__": "ScheduleItem", "job": "ID00095_000", "start_time": 389.25866666666667}, {"end_time": 406.4666666666667, "state": "finished", "__cls__": "ScheduleItem", "job": "ID00094_000", "start_time": 397.8826666666667}, {"end_time": 415.0186666666667, "state": "finished", "__cls__": "ScheduleItem", "job": "ID00093_000", "start_time": 406.4666666666667}, {"end_time": 423.7226666666667, "state": "finished", "__cls__": "ScheduleItem", "job": "ID00080_000", "start_time": 415.0186666666667}, {"end_time": 432.3146666666667, "state": "finished", "__cls__": "ScheduleItem", "job": "ID00090_000", "start_time": 423.7226666666667}, {"end_time": 441.0826666666667, "state": "finished", "__cls__": "ScheduleItem", "job": "ID00081_000", "start_time": 432.3146666666667}, {"end_time": 449.6666666666667, "state": "finished", "__cls__": "ScheduleItem", "job": "ID00083_000", "start_time": 441.0826666666667}, {"end_time": 458.3866666666667, "state": "finished", "__cls__": "ScheduleItem", "job": "ID00086_000", "start_time": 449.6666666666667}, {"end_time": 464.4906666666667, "state": "finished", "__cls__": "ScheduleItem", "job": "ID00096_000", "start_time": 458.3866666666667}, {"end_time": 472.1706666666667, "state": "finished", "__cls__": "ScheduleItem", "job": "ID00097_000", "start_time": 464.4906666666667}, {"end_time": 477.6986666666667, "state": "finished", "__cls__": "ScheduleItem", "job": "ID00098_000", "start_time": 472.1706666666667}, {"end_time": 478.3626666666667, "state": "finished", "__cls__": "ScheduleItem", "job": "ID00099_000", "start_time": 477.6986666666667}], "node": "res_0_node_2"}, {"value": [{"end_time": 9.053333333333335, "state": "finished", "__cls__": "ScheduleItem", "job": "ID00015_000", "start_time": 0}, {"end_time": 17.96, "state": "finished", "__cls__": "ScheduleItem", "job": "ID00013_000", "start_time": 9.053333333333335}, {"end_time": 27.046666666666667, "state": "finished", "__cls__": "ScheduleItem", "job": "ID00008_000", "start_time": 17.96}, {"end_time": 34.12, "state": "finished", "__cls__": "ScheduleItem", "job": "ID00075_000", "start_time": 27.046666666666667}, {"end_time": 42.95333333333333, "state": "finished", "__cls__": "ScheduleItem", "job": "ID00006_000", "start_time": 34.12}, {"end_time": 50.13333333333333, "state": "finished", "__cls__": "ScheduleItem", "job": "ID00041_000", "start_time": 42.95333333333333}, {"end_time": 59.266666666666666, "state": "finished", "__cls__": "ScheduleItem", "job": "ID00009_000", "start_time": 50.13333333333333}, {"end_time": 68.47333333333333, "state": "finished", "__cls__": "ScheduleItem", "job": "ID00011_000", "start_time": 59.266666666666666}, {"end_time": 75.50666666666666, "state": "finished", "__cls__": "ScheduleItem", "job": "ID00053_000", "start_time": 68.47333333333333}, {"end_time": 82.40666666666667, "state": "finished", "__cls__": "ScheduleItem", "job": "ID00063_000", "start_time": 75.50666666666666}, {"end_time": 89.44, "state": "finished", "__cls__": "ScheduleItem", "job": "ID00051_000", "start_time": 82.40666666666667}, {"end_time": 98.38666666666666, "state": "finished", "__cls__": "ScheduleItem", "job": "ID00002_000", "start_time": 89.44}, {"end_time": 105.65999999999998, "state": "finished", "__cls__": "ScheduleItem", "job": "ID00030_000", "start_time": 98.38666666666666}, {"end_time": 112.75999999999998, "state": "finished", "__cls__": "ScheduleItem", "job": "ID00073_000", "start_time": 105.65999999999998}, {"end_time": 119.83333333333331, "state": "finished", "__cls__": "ScheduleItem", "job": "ID00033_000", "start_time": 112.75999999999998}, {"end_time": 134.08, "state": "finished", "__cls__": "ScheduleItem", "job": "ID00038_000", "start_time": 127.14}, {"end_time": 141.2266666666667, "state": "finished", "__cls__": "ScheduleItem", "job": "ID00059_000", "start_time": 134.08}, {"end_time": 148.27333333333337, "state": "finished", "__cls__": "ScheduleItem", "job": "ID00028_000", "start_time": 141.2266666666667}, {"end_time": 155.38000000000002, "state": "finished", "__cls__": "ScheduleItem", "job": "ID00069_000", "start_time": 148.27333333333337}, {"end_time": 162.45333333333335, "state": "finished", "__cls__": "ScheduleItem", "job": "ID00024_000", "start_time": 155.38000000000002}, {"end_time": 169.38666666666668, "state": "finished", "__cls__": "ScheduleItem", "job": "ID00043_000", "start_time": 162.45333333333335}, {"end_time": 176.39333333333335, "state": "finished", "__cls__": "ScheduleItem", "job": "ID00057_000", "start_time": 169.38666666666668}, {"end_time": 183.49333333333334, "state": "finished", "__cls__": "ScheduleItem", "job": "ID00077_000", "start_time": 176.39333333333335}, {"end_time": 190.55333333333334, "state": "finished", "__cls__": "ScheduleItem", "job": "ID00047_000", "start_time": 183.49333333333334}, {"end_time": 197.65333333333334, "state": "finished", "__cls__": "ScheduleItem", "job": "ID00050_000", "start_time": 190.55333333333334}, {"end_time": 204.67333333333335, "state": "finished", "__cls__": "ScheduleItem", "job": "ID00035_000", "start_time": 197.65333333333334}, {"end_time": 211.7266666666667, "state": "finished", "__cls__": "ScheduleItem", "job": "ID00025_000", "start_time": 204.67333333333335}], "node": "res_0_node_3"}], "__cls__": "Schedule"}, "ideal_flops": 20, "dedicated_resources": [{"name": "res_0", "__cls__": "Resource", "nodes": [{"flops": 10, "name": "res_0_node_0", "soft": ["any_soft"], "__cls__": "Node", "resource": "res_0"}, {"flops": 15, "name": "res_0_node_1", "soft": ["any_soft"], "__cls__": "Node", "resource": "res_0"}, {"flops": 25, "name": "res_0_node_2", "soft": ["any_soft"], "__cls__": "Node", "resource": "res_0"}, {"flops": 30, "name": "res_0_node_3", "soft": ["any_soft"], "__cls__": "Node", "resource": "res_0"}]}], "transfer_mx": "{\"res_0_node_0\": {\"res_0_node_0\": 0, \"res_0_node_1\": 215411242, \"res_0_node_2\": 292994926, \"res_0_node_3\": 204071513}, \"res_0_node_1\": {\"res_0_node_0\": 592324428, \"res_0_node_1\": 0, \"res_0_node_2\": 661669541, \"res_0_node_3\": 999807284}, \"res_0_node_2\": {\"res_0_node_0\": 951831115, \"res_0_node_1\": 590472006, \"res_0_node_2\": 0, \"res_0_node_3\": 420183956}, \"res_0_node_3\": {\"res_0_node_0\": 802972819, \"res_0_node_1\": 666550781, \"res_0_node_2\": 285516961, \"res_0_node_3\": 0}}", "__cls__": "SaveBundle", "name": "Montage_100_bundle", "wf_name": "Montage_100"}